[{"StaID":14501,"ID":1,"Name":"Stung Treng","type":"WL 7PM","week1":9.01,"week2":7.9725},{"StaID":14901,"ID":2,"Name":"Kratie","type":"WL 7PM","week1":19.57875,"week2":18.515},{"StaID":19802,"ID":3,"Name":"Kompong Cham","type":"WL 7PM","week1":12.64625,"week2":12.18375},{"StaID":33401,"ID":4,"Name":"Bassac Chaktomuk","type":"WL 7PM","week1":7.77625,"week2":7.80125},{"StaID":20101,"ID":5,"Name":"Phnom Penh Port","type":"WL 7PM","week1":6.6175,"week2":6.56875},{"StaID":19806,"ID":6,"Name":"Neak Luong","type":"WL 7PM","week1":5.51,"week2":5.6425},{"StaID":33402,"ID":7,"Name":"Koh Khel","type":"WL 7PM","week1":6.77125,"week2":6.86375},{"StaID":20102,"ID":8,"Name":"Prek Kdam","type":"WL 7PM","week1":6.525,"week2":6.7925},{"StaID":20106,"ID":9,"Name":"Kompong Luong","type":"WL 7PM","week1":5.24875,"week2":5.84875},{"StaID":440102,"ID":10,"Name":"Voeun Sai","type":"WL 7PM","week1":4.58125,"week2":3.98125},{"StaID":600101,"ID":11,"Name":"Kompong Chen","type":"WL 7PM","week1":5.54375,"week2":5.33625},{"StaID":20103,"ID":12,"Name":"Kompong Chhnang","type":"WL 7PM","week1":7.49125,"week2":7.9575},{"StaID":570101,"ID":13,"Name":"Kompong Kdei","type":"WL 7PM","week1":4.67625,"week2":6.14625},{"StaID":620101,"ID":14,"Name":"Kompong Thmar","type":"WL 7PM","week1":4.51875,"week2":4.44875},{"StaID":450101,"ID":15,"Name":"Lumphat","type":"WL 7PM","week1":6.655,"week2":6.09},{"StaID":110404,"ID":30,"Name":"Kompong Speu","type":"WL 7PM","week1":null,"week2":null},{"StaID":120423,"ID":40,"Name":"Stung Chinit","type":"WL 7PM","week1":null,"week2":null},{"StaID":104274,"ID":50,"Name":"Anlong Thoam","type":"WL 7PM","week1":null,"week2":null},{"StaID":104201,"ID":51,"Name":"Thmey","type":"WL 7PM","week1":null,"week2":null},{"StaID":104279,"ID":52,"Name":"Chong Thnoi","type":"WL 7PM","week1":null,"week2":null},{"StaID":104251,"ID":53,"Name":"Ou Koki","type":"WL 7PM","week1":null,"week2":null},{"StaID":104267,"ID":54,"Name":"Champei","type":"WL 7PM","week1":null,"week2":null},{"StaID":104191,"ID":55,"Name":"Krang Thom","type":"WL 7PM","week1":null,"week2":null},{"StaID":104203,"ID":56,"Name":"Serei Vong","type":"WL 7PM","week1":null,"week2":null},{"StaID":140204,"ID":57,"Name":"Dei Dos","type":"WL 7PM","week1":null,"week2":null},{"StaID":104222,"ID":58,"Name":"Tang Sya","type":"WL 7PM","week1":null,"week2":null},{"StaID":104231,"ID":59,"Name":"Krang Serei","type":"WL 7PM","week1":null,"week2":null},{"StaID":104268,"ID":60,"Name":"Sre Trapang","type":"WL 7PM","week1":null,"week2":null},{"StaID":104217,"ID":61,"Name":"Roluos","type":"WL 7PM","week1":null,"week2":null},{"StaID":104289,"ID":62,"Name":"Krang Svay","type":"WL 7PM","week1":null,"week2":null},{"StaID":104207,"ID":63,"Name":"Krang Samre","type":"WL 7PM","week1":null,"week2":null},{"StaID":92600,"ID":64,"Name":"Jinghong","type":"WL 7PM","week1":537.71,"week2":537.09875},{"StaID":92980,"ID":65,"Name":"Manan","type":"WL 7PM","week1":532.9075,"week2":532.9875},{"StaID":10402,"ID":66,"Name":"Xieng Kok","type":"WL 7PM","week1":null,"week2":null},{"StaID":10901,"ID":67,"Name":"Pak Beng","type":"WL 7PM","week1":12.76625,"week2":12.265},{"StaID":11201,"ID":68,"Name":"Luang Prabang","type":"WL 7PM","week1":10.895,"week2":10.86},{"StaID":11401,"ID":69,"Name":"Paklay","type":"WL 7PM","week1":6.37,"week2":6.9625},{"StaID":11901,"ID":70,"Name":"Vientiane","type":"WL 7PM","week1":7.1825,"week2":7.1725},{"StaID":12703,"ID":71,"Name":"Paksane","type":"WL 7PM","week1":8.38375,"week2":8.33625},{"StaID":13102,"ID":72,"Name":"Thakhek","type":"WL 7PM","week1":9.44375,"week2":8.815},{"StaID":13401,"ID":73,"Name":"Savannakhet","type":"WL 7PM","week1":7.1725,"week2":6.24625},{"StaID":13901,"ID":74,"Name":"Pakse","type":"WL 7PM","week1":9.54125,"week2":8.52375},{"StaID":230101,"ID":75,"Name":"Ban Pak Kanhoung","type":"WL 7PM","week1":5.38625,"week2":5.3025},{"StaID":250101,"ID":76,"Name":"Muong Mai","type":"WL 7PM","week1":3.44,"week2":3.55},{"StaID":270101,"ID":77,"Name":"Ban Phone Si","type":"WL 7PM","week1":6.54625,"week2":6.355},{"StaID":260101,"ID":78,"Name":"Muang Kao","type":"WL 7PM","week1":4.0875,"week2":3.845},{"StaID":320107,"ID":79,"Name":"Mahaxai","type":"WL 7PM","week1":13.905,"week2":10.71875},{"StaID":390102,"ID":80,"Name":"Khong Sedone","type":"WL 7PM","week1":5.9671428571,"week2":5.295},{"StaID":390103,"ID":81,"Name":"Saravanne","type":"WL 7PM","week1":2.28375,"week2":2.675},{"StaID":430106,"ID":82,"Name":"Veun Khen","type":"WL 7PM","week1":7.865,"week2":7.455},{"StaID":430105,"ID":83,"Name":"Veun Khen","type":"WL 7PM","week1":5.3925,"week2":5.22375},{"StaID":100102,"ID":84,"Name":"Muong Ngoy","type":"WL 7PM","week1":6.4675,"week2":6.50875},{"StaID":120101,"ID":85,"Name":"Ban Mixay","type":"WL 7PM","week1":null,"week2":null},{"StaID":190103,"ID":86,"Name":"Sayaboury","type":"WL 7PM","week1":null,"week2":null},{"StaID":190205,"ID":87,"Name":"Xieng Ngeun","type":"WL 7PM","week1":null,"week2":null},{"StaID":180207,"ID":88,"Name":"Vang Vieng","type":"WL 7PM","week1":2.0275,"week2":2.0225},{"StaID":230113,"ID":89,"Name":"Phiengluang","type":"WL 7PM","week1":1.16875,"week2":1.2225},{"StaID":200204,"ID":90,"Name":"Oudomxay","type":"WL 7PM","week1":null,"week2":null},{"StaID":210201,"ID":91,"Name":"Phongsaly","type":"WL 7PM","week1":null,"week2":null},{"StaID":200101,"ID":92,"Name":"Moung Namtha","type":"WL 7PM","week1":null,"week2":null},{"StaID":270903,"ID":93,"Name":"Ban Signo","type":"WL 7PM","week1":null,"week2":null},{"StaID":190302,"ID":94,"Name":"Xiengkhouang","type":"WL 7PM","week1":null,"week2":null},{"StaID":14301,"ID":95,"Name":"Ban Chan Noi","type":"WL 7PM","week1":null,"week2":null},{"StaID":350101,"ID":97,"Name":"Ban Keng Don","type":"WL 7PM","week1":8.898,"week2":7.95375},{"StaID":350401,"ID":98,"Name":"Highway Bridge","type":"WL 7PM","week1":19.2725,"week2":15.7925},{"StaID":390104,"ID":100,"Name":"Souvanna Khill","type":"WL 7PM","week1":8.27125,"week2":7.93},{"StaID":150609,"ID":107,"Name":"Sekong","type":"WL 7PM","week1":2.64375,"week2":3.62125},{"StaID":270502,"ID":109,"Name":"Ban Nape","type":"WL 7PM","week1":null,"week2":null},{"StaID":320101,"ID":110,"Name":"Se Ban Fai","type":"WL 7PM","week1":null,"week2":null},{"StaID":10501,"ID":111,"Name":"Chiang Saen","type":"WL 7PM","week1":4.32875,"week2":3.9825},{"StaID":10801,"ID":112,"Name":"Chiang Khong","type":"WL 7PM","week1":3.92125,"week2":3.72375},{"StaID":11903,"ID":113,"Name":"Chiang Khan","type":"WL 7PM","week1":9.27,"week2":9.12625},{"StaID":12001,"ID":114,"Name":"Nong Khai","type":"WL 7PM","week1":6.82375,"week2":6.8975},{"StaID":13101,"ID":115,"Name":"Nakhon Phanom","type":"WL 7PM","week1":8.36875,"week2":7.77875},{"StaID":13402,"ID":116,"Name":"Mukdahan","type":"WL 7PM","week1":8.75375,"week2":7.8325},{"StaID":13801,"ID":117,"Name":"Khong Chiam","type":"WL 7PM","week1":11.46875,"week2":10.4175},{"StaID":50115,"ID":118,"Name":"Ban Mai Bua Daeng","type":"WL 7PM","week1":null,"week2":null},{"StaID":50106,"ID":119,"Name":"Doi Hang","type":"WL 7PM","week1":2.71625,"week2":2.06625},{"StaID":70103,"ID":120,"Name":"Thoeng","type":"WL 7PM","week1":4.31,"week2":4.26125},{"StaID":150101,"ID":121,"Name":"Wang Saphung","type":"WL 7PM","week1":4.11125,"week2":3.00625},{"StaID":290102,"ID":122,"Name":"Ban Tha Kok Daeng","type":"WL 7PM","week1":13.04625,"week2":12.88875},{"StaID":290113,"ID":123,"Name":"Ban Had Paeng","type":"WL 7PM","week1":10.74375,"week2":10.33125},{"StaID":50104,"ID":124,"Name":"Chiang Rai","type":"WL 7PM","week1":3.545,"week2":3.14125},{"StaID":380103,"ID":125,"Name":"Ubon","type":"WL 7PM","week1":null,"week2":null},{"StaID":19803,"ID":126,"Name":"Tan Chau","type":"WL 7PM","week1":2.295,"week2":2.54875},{"StaID":39801,"ID":127,"Name":"Chau Doc","type":"WL 7PM","week1":1.96875,"week2":2.29625},{"StaID":980601,"ID":128,"Name":"Vam Nao","type":"WL 7PM","week1":1.85125,"week2":2.04625},{"StaID":19804,"ID":129,"Name":"My Thuan","type":"WL 7PM","week1":1.0875,"week2":0.075},{"StaID":39803,"ID":130,"Name":"Can Tho","type":"WL 7PM","week1":1.255,"week2":0.57125},{"StaID":985203,"ID":131,"Name":"Vam Kenh","type":"WL 7PM","week1":0.2825,"week2":-1.04625},{"StaID":451305,"ID":132,"Name":"Ban Don","type":"WL 7PM","week1":70.19125,"week2":70.2125},{"StaID":440201,"ID":133,"Name":"Kon Tum","type":"WL 7PM","week1":15.82875,"week2":15.88},{"StaID":450701,"ID":134,"Name":"Duc Xuyen","type":"WL 7PM","week1":22.08,"week2":22.2175}]